okapi_em/__init__.py
okapi_em/_widget.py
okapi_em/filters.py
okapi_em/measure_charging.py
okapi_em/napari.yaml
okapi_em/quoll_wrapper.py
okapi_em/slice_alignment.py
okapi_em/_tests/__init__.py
okapi_em/_tests/test_slice_alignment.py
okapi_em/_tests/test_widget.py
okapi_em-0.0.10.dist-info/LICENSE
okapi_em-0.0.10.dist-info/METADATA
okapi_em-0.0.10.dist-info/WHEEL
okapi_em-0.0.10.dist-info/entry_points.txt
okapi_em-0.0.10.dist-info/top_level.txt
okapi_em-0.0.10.dist-info/RECORD
