Metadata-Version: 2.1
Name: okapi-em
Version: 0.0.10
Summary: napari plugin to deal with charging artifacts in tomography electron microscopy data
Author: Luis Perdigao
Author-email: luis.perdigao@rfi.ac.uk
License: Apache-2.0
Classifier: Development Status :: 2 - Pre-Alpha
Classifier: Intended Audience :: Developers
Classifier: Framework :: napari
Classifier: Topic :: Software Development :: Testing
Classifier: Programming Language :: Python
Classifier: Programming Language :: Python :: 3
Classifier: Programming Language :: Python :: 3.7
Classifier: Programming Language :: Python :: 3.8
Classifier: Programming Language :: Python :: 3.9
Classifier: Programming Language :: Python :: 3.10
Classifier: Operating System :: OS Independent
Classifier: License :: OSI Approved :: Apache Software License
Requires-Python: >=3.7
License-File: LICENSE
Requires-Dist: numpy
Requires-Dist: magicgui
Requires-Dist: chafer
Requires-Dist: napari[all]
Requires-Dist: opencv-python
Requires-Dist: quoll >=0.0.4
Provides-Extra: all
Requires-Dist: imageio-ffmpeg ; extra == 'all'
Provides-Extra: testing
Requires-Dist: tox ; extra == 'testing'
Requires-Dist: pytest ; extra == 'testing'
Requires-Dist: pytest-cov ; extra == 'testing'
Requires-Dist: pytest-qt ; extra == 'testing'
